{
  "title": "구글 Adsense 미국 세금 정보 입력하는 방법",
  "slug": "google-adsense-us-tax-info-entry",
  "content": "## 1. 개요\n\n구글은 법적으로 광고 수익에 대해 세금 정보를 수집하고 보고할 의무가 있다. 구글 법인에서 수입을 지급받기 위해서는 미국과 싱가포르 요청에 따라 세금 정보를 입력해야 한다.\n\n정확한 세금 정보를 제공하지 않으면 수익 지급이 지연되거나 중단될 수 있다고 한다. 또한 세금 정보가 없으면 최대 30%의 세금 원천 징수가 적용될 수 있어 올바른 세금 정보를 입력하는 것이 중요하다.\n\n세금 정보를 입력하지 않았다면 `지급` > `지급 정보` > `세금 정보 관리`에서 추가해야 하는 세금 정보를 확인할 수 있다.\n\n- 미국 세금 정보\n- 싱가포르 세금 정보\n  - 싱가포르 세금 정보 입력은 추가로 준비해야 하는 서류도 있어서 다른 글로 포스팅할 예정이다\n\n![](image-20240707083903316.png)\n\n미국 세금 정보는 사업자가 아닌 개인으로 제출하는 방법으로 작성한다.\n\n## 2. 미국 세금 정보 입력하기\n\n![](image-20240707083917992.png)\n\n`세금 정보 관리` 목록에서 `미국` > `세금정보 추가` 버튼을 클릭하고 세금 정보 입력을 시작하기 위해 `시작하기 전에` 창에서 `양식 시작` 버튼을 클릭한다.\n\n![](image-20240707083930316.png)\n\n보인 인증을 다시 확인하기 위해서 로그인 창이 뜨고 로그인 비밀번호를 입력한다.\n\n### 2.1 미국 세금 정보\n\n![](image-20240707084124346.png)\n\n- 계좌 유형\n  - 개인 : 사업자가 아니라서 `개인`을 선택한다.\n- 세금 약식 유형\n  - `W-8BEN`은 미국 외 국가의 개인이 주로 사용하는 양식이라 이 유형을 선택한다\n\n### 2.2 W-8BEN 세금 양식\n\n![](image-20240707084147307.png)\n\n1. `수익권자에 해당하는 개인의 이름`: 영문으로 작성하는 것이 좋다\n2. `DBA(상호) 또는 불인정 법인` : 개인은 입력하지 않아도 된다\n3. `시민권을 보유한 국가/지역` : `대한민국`을 선택하면 된다\n4. `납세자 식별 번호`: 개인인 경우 이 부분은 스킵한다\n\n#### 2.2.1 주소\n\n![](image-20240707084202717.png)\n\n1. 주소에는 영문으로 주소를 입력한다.\n2. `우편 주소가 영구 거주지 주소와 동일합니다`에 체크를 한다.\n\n> 영문 주소는 [영문 주소변환](https://www.jusoen.com/) 사이트를 이용하는 걸 추천합니다.\n\n#### 2.2.2 조세조약\n\n![](image-20240707084211711.png)\n\n조세 조약에 따라 인하된 원청징수세율을 제출을 신청하시나요?\n\n1. `아니오`: 개인의 경우에는 `아니요`를 선택한다\n2. `예` : 사업자인 경우에는 `예`를 선택한다. 조세 조약 체결에 따라서 10% 가량 세금 혜택이 있기 때문에 사업자이신 분들은 신청하기를 추천한다.\n\n#### 2.2.3 미국에서 수행한 활동 및 서비스\n\n![](image-20240707084222152.png)\n\n미국에서 수행한 활동 및 서비스\n\n- 미국 밖에서 행해지는 거라 해당상황이 없어서 `아니요`에 체크한다\n- Google 또는 Goolge 제휴사에 제공하는 서비스가 미국 밖에서… 이 부분도 체크한다\n\n#### 2.2.4 세금 신고\n\n![](image-20240707084231771.png)\n\n세금 정보를 우편으로 받기보다는 이메일로 받는 게 더 수월하기 때문에 여기서도 권장하고 있다.\n\n1. `우편 주신 중지(권장)`을 선택하고 `우편 수진 중이에 동의합니다`에도 체크한다.\n\n### 2.2.5 문서 미리보기\n\n![](image-20240707084239007.png)\n\n문서 미리보기에서는 `생성된 세무 서류를 본인이 알고…. 완전함을 확인합니다`에 체크하고 `다음` 버튼을 클릭한다.\n\n#### 2.2.6 인증 및 서명\n\n아래와 같이 해당 옵션을 체크하고 제출 `버튼`을 클릭하여 마무리를 한다.\n\n![](image-20240707084246155.png)\n\n## 3. 마무리\n\n등록하면 바로 상태: `승인됨`이 표시된다.\n\n![](image-20240707084253673.png)\n\n다음 포스팅에서는 싱가포르 세금 정보 입력을 다룰 예정이다.\n\n## 4. 참고\n\n- [구글 Google 애드센스 미국 세금 정보 제출하는 방법](https://orangeyoung-37.tistory.com/92)\n- [애드센스 미국 세금 정보 작성하자](https://moonnote.tistory.com/321)\n- [개인사업자 애드센스 미국 세금 정보 제출, 싱가포르 세금 정보, 판매 대금 지급 지연](https://dathru.com/애드센스-미국-세금-정보-제출-싱가포르-세금-정보/)",
  "excerpt": "구글은 법적으로 광고 수익에 대해 세금 정보를 수집하고 보고할 의무가 있다. 구글 법인에서 수입을 지급받기 위해서는 미국과 싱가포르 요청에 따라 세금 정보를 입력해야 한다. 정확한 세금 정보를 제공하지 않으면 수익 지급이 지연되거나 중단될 수 있다고 한다. 또한 세금 ...",
  "category": "Etc",
  "tags": [
    "구글 애드센스",
    "adsense",
    "미국 세금정보",
    "부업",
    "광고수입",
    "애드센스",
    "블로그 부업"
  ],
  "series": null,
  "featuredImage": "/contents/etc/google-adsense-us-tax-info-entry/image-20240707083903316.png",
  "published": true,
  "seoTitle": "구글 Adsense 미국 세금 정보 입력하는 방법 | 투자 인사이트",
  "seoDescription": "구글 Adsense 미국 세금 정보 입력하는 방법",
  "seoKeywords": "구글 애드센스, adsense, 미국 세금정보, 부업, 광고수입, 애드센스, 블로그 부업",
  "date": "2024-07-07",
  "createdAt": "2024-07-07",
  "updatedAt": "2024-07-07",
  "views": 0,
  "likes": 0
}